[
    [
        {
            "fid": 0,
            "type": "FRAME",
            "name": "BattleNetCustomLoadPanel",
            "inherits": "",
            "fields": [
                {
                    "type": "Field",
                    "name": "SetAllPoints,",
                    "child": []
                },
                {
                    "type": "Field",
                    "name": "TabFocusPush,",
                    "child": []
                }
            ],
            "child": [
                {
                    "fid": 1,
                    "type": "FRAME",
                    "name": "GameSettingsPanel",
                    "inherits": "",
                    "fields": [],
                    "child": [
                        {
                            "fid": 2,
                            "type": "TEXT",
                            "name": "BattleNetCustomLoadTitle",
                            "inherits": "BattleNetTitleTextTemplate",
                            "fields": [
                                {
                                    "type": "Field",
                                    "name": "SetPoint",
                                    "child": [
                                        "TOPLEFT,",
                                        "BattleNetCustomLoadPanel,",
                                        "TOPLEFT,",
                                        "0.02625,",
                                        "-0.039,"
                                    ]
                                },
                                {
                                    "type": "Field",
                                    "name": "Text",
                                    "child": [
                                        "LOAD_MULTIPLAYER_SAVED_GAME,"
                                    ]
                                }
                            ],
                            "child": []
                        },
                        {
                            "fid": 3,
                            "type": "TEXT",
                            "name": "CreateGameNameLabel",
                            "inherits": "BattleNetLabelTextTemplate",
                            "fields": [
                                {
                                    "type": "Field",
                                    "name": "SetPoint",
                                    "child": [
                                        "TOPLEFT,",
                                        "BattleNetCustomLoadTitle,",
                                        "BOTTOMLEFT,",
                                        "0.0,",
                                        "-0.01625,"
                                    ]
                                },
                                {
                                    "type": "Field",
                                    "name": "Text",
                                    "child": [
                                        "COLON_GAME_NAME,"
                                    ]
                                }
                            ],
                            "child": []
                        },
                        {
                            "fid": 4,
                            "type": "EDITBOX",
                            "name": "CreateGameNameEditBox",
                            "inherits": "BattleNetEditBoxTemplate",
                            "fields": [
                                {
                                    "type": "Field",
                                    "name": "Width",
                                    "child": [
                                        "0.2375,"
                                    ]
                                },
                                {
                                    "type": "Field",
                                    "name": "SetPoint",
                                    "child": [
                                        "TOPLEFT,",
                                        "CreateGameNameLabel,",
                                        "BOTTOMLEFT,",
                                        "0.0,",
                                        "-0.001,"
                                    ]
                                },
                                {
                                    "type": "Field",
                                    "name": "TabFocusDefault,",
                                    "child": []
                                },
                                {
                                    "type": "Field",
                                    "name": "TabFocusNext",
                                    "child": [
                                        "OKButton,"
                                    ]
                                },
                                {
                                    "type": "Field",
                                    "name": "EditTextFrame",
                                    "child": [
                                        "CreateGameNameEditBoxText,"
                                    ]
                                }
                            ],
                            "child": [
                                {
                                    "fid": 5,
                                    "type": "TEXT",
                                    "name": "CreateGameNameEditBoxText",
                                    "inherits": "BattleNetEditBoxTextTemplate",
                                    "fields": [],
                                    "child": []
                                }
                            ]
                        },
                        {
                            "fid": 6,
                            "type": "FRAME",
                            "name": "FileListFrame",
                            "inherits": "",
                            "fields": [
                                {
                                    "type": "Field",
                                    "name": "SetPoint",
                                    "child": [
                                        "TOPLEFT,",
                                        "CreateGameNameLabel,",
                                        "BOTTOMLEFT,",
                                        "0.0,",
                                        "-0.04,"
                                    ]
                                },
                                {
                                    "type": "Field",
                                    "name": "Width",
                                    "child": [
                                        "0.37,"
                                    ]
                                },
                                {
                                    "type": "Field",
                                    "name": "Height",
                                    "child": [
                                        "0.23,"
                                    ]
                                }
                            ],
                            "child": []
                        },
                        {
                            "fid": 7,
                            "type": "TEXT",
                            "name": "LoadInfoText",
                            "inherits": "BattleNetValueTextTemplate",
                            "fields": [
                                {
                                    "type": "Field",
                                    "name": "SetPoint",
                                    "child": [
                                        "TOPLEFT,",
                                        "FileListFrame,",
                                        "BOTTOMLEFT,",
                                        "0.0,",
                                        "-0.004,"
                                    ]
                                },
                                {
                                    "type": "Field",
                                    "name": "Width",
                                    "child": [
                                        "0.37,"
                                    ]
                                },
                                {
                                    "type": "Field",
                                    "name": "Text",
                                    "child": [
                                        "LOAD_BATTLENET_INFO,"
                                    ]
                                }
                            ],
                            "child": []
                        }
                    ]
                },
                {
                    "fid": 8,
                    "type": "FRAME",
                    "name": "MapInfoPaneContainer",
                    "inherits": "",
                    "fields": [
                        {
                            "type": "Field",
                            "name": "Width",
                            "child": [
                                "0.271875,"
                            ]
                        },
                        {
                            "type": "Field",
                            "name": "Height",
                            "child": [
                                "0.223125,"
                            ]
                        },
                        {
                            "type": "Field",
                            "name": "SetPoint",
                            "child": [
                                "TOP,",
                                "BattleNetCustomLoadPanel,",
                                "TOPRIGHT,",
                                "-0.180625,",
                                "-0.0375,"
                            ]
                        }
                    ],
                    "child": []
                },
                {
                    "fid": 9,
                    "type": "BACKDROP",
                    "name": "OKBackdrop",
                    "inherits": "BattleNetMenuButtonBaseBackdrop",
                    "fields": [
                        {
                            "type": "Field",
                            "name": "Width",
                            "child": [
                                "0.24,"
                            ]
                        },
                        {
                            "type": "Field",
                            "name": "SetPoint",
                            "child": [
                                "TOPRIGHT,BattleNetCustomLoadPanel,BOTTOMRIGHT,",
                                "-0.014375,",
                                "0.124375,"
                            ]
                        }
                    ],
                    "child": [
                        {
                            "fid": 10,
                            "type": "GLUETEXTBUTTON",
                            "name": "OKButton",
                            "inherits": "BattleNetButtonTemplate",
                            "fields": [
                                {
                                    "type": "Field",
                                    "name": "Width",
                                    "child": [
                                        "0.168,"
                                    ]
                                },
                                {
                                    "type": "Field",
                                    "name": "SetPoint",
                                    "child": [
                                        "TOPRIGHT,OKBackdrop,TOPRIGHT,",
                                        "-0.012,",
                                        "-0.0165,"
                                    ]
                                },
                                {
                                    "type": "Field",
                                    "name": "ControlShortcutKey",
                                    "child": [
                                        "L,"
                                    ]
                                },
                                {
                                    "type": "Field",
                                    "name": "TabFocusNext",
                                    "child": [
                                        "CancelButton,"
                                    ]
                                },
                                {
                                    "type": "Field",
                                    "name": "ButtonText",
                                    "child": [
                                        "OKButtonText,"
                                    ]
                                }
                            ],
                            "child": [
                                {
                                    "fid": 11,
                                    "type": "TEXT",
                                    "name": "OKButtonText",
                                    "inherits": "BattleNetButtonTextTemplate",
                                    "fields": [
                                        {
                                            "type": "Field",
                                            "name": "Text",
                                            "child": [
                                                "KEY_LOAD_GAME,"
                                            ]
                                        }
                                    ],
                                    "child": []
                                }
                            ]
                        }
                    ]
                },
                {
                    "fid": 12,
                    "type": "BACKDROP",
                    "name": "CancelBackdrop",
                    "inherits": "BattleNetMenuButtonBaseBackdrop",
                    "fields": [
                        {
                            "type": "Field",
                            "name": "Width",
                            "child": [
                                "0.24,"
                            ]
                        },
                        {
                            "type": "Field",
                            "name": "SetPoint",
                            "child": [
                                "TOPRIGHT,OKBackdrop,BOTTOMRIGHT,",
                                "0.0,",
                                "0.015,"
                            ]
                        }
                    ],
                    "child": [
                        {
                            "fid": 13,
                            "type": "GLUETEXTBUTTON",
                            "name": "CancelButton",
                            "inherits": "BattleNetButtonTemplate",
                            "fields": [
                                {
                                    "type": "Field",
                                    "name": "Width",
                                    "child": [
                                        "0.168,"
                                    ]
                                },
                                {
                                    "type": "Field",
                                    "name": "SetPoint",
                                    "child": [
                                        "TOPRIGHT,CancelBackdrop,TOPRIGHT,",
                                        "-0.012,",
                                        "-0.0165,"
                                    ]
                                },
                                {
                                    "type": "Field",
                                    "name": "ControlShortcutKey",
                                    "child": [
                                        "B,"
                                    ]
                                },
                                {
                                    "type": "Field",
                                    "name": "TabFocusNext",
                                    "child": [
                                        "CreateGameNameEditBox,"
                                    ]
                                },
                                {
                                    "type": "Field",
                                    "name": "ButtonText",
                                    "child": [
                                        "CancelButtonText,"
                                    ]
                                }
                            ],
                            "child": [
                                {
                                    "fid": 14,
                                    "type": "TEXT",
                                    "name": "CancelButtonText",
                                    "inherits": "BattleNetButtonTextTemplate",
                                    "fields": [
                                        {
                                            "type": "Field",
                                            "name": "Text",
                                            "child": [
                                                "KEY_BACK,"
                                            ]
                                        }
                                    ],
                                    "child": []
                                }
                            ]
                        }
                    ]
                }
            ]
        }
    ]
]